feather_df_cli/__init__.py
feather_df_cli/cli.py
feather_df_cli-0.1.3.dist-info/LICENSE.md
feather_df_cli-0.1.3.dist-info/METADATA
feather_df_cli-0.1.3.dist-info/WHEEL
feather_df_cli-0.1.3.dist-info/entry_points.txt
feather_df_cli-0.1.3.dist-info/top_level.txt
feather_df_cli-0.1.3.dist-info/RECORD
