Metadata-Version: 2.2
Name: feather-df-cli
Version: 0.1.3
Summary: A CLI tool for reading and displaying Feather data format files
Home-page: https://github.com/villadora/feather-df-cli
Author: villadora
Classifier: Programming Language :: Python :: 3
Classifier: License :: OSI Approved :: MIT License
Classifier: Operating System :: OS Independent
Requires-Python: >=3.6
License-File: LICENSE.md
Requires-Dist: pyarrow>=12.0.1
Requires-Dist: tabulate>=0.9.0
Dynamic: author
Dynamic: classifier
Dynamic: description
Dynamic: description-content-type
Dynamic: home-page
Dynamic: requires-dist
Dynamic: requires-python
Dynamic: summary
